rdfobj
