Metadata-Version: 2.1
Name: rdfobj
Version: 0.3.4
Summary: A python library for object to triple mapping using OWL
Home-page: https://forge.inrae.fr/pegase/rdfobject
Author: FJR Moreews
Author-email: francois.moreews@inrae.fr
License: CECILL-B
Platform: Posix; MacOS X;
Classifier: Development Status :: 4 - Beta
Classifier: Intended Audience :: Developers
Classifier: Intended Audience :: Science/Research
Classifier: License :: CeCILL-B Free Software License Agreement (CECILL-B)
Classifier: Programming Language :: Python :: 3.9
Classifier: Programming Language :: Python :: 3.11
Classifier: Topic :: Scientific/Engineering
Classifier: Topic :: Scientific/Engineering :: Bio-Informatics
Requires-Python: >=3.8.10
Provides-Extra: testing
